Workbook

Sheet Department
A1: 處編號 | B1: 部門 編號 | C1: 部門名稱(中文) | D1: 部門名稱(英文) | E1: 活躍 | F1: 隱藏
A2: Division Code | B2: Department Code | C2: Department Name (Chi) | D2: Department Name (Eng) | E2: IsActive | F2: Invisible | G2: MDM Department
A3: 10_PD | B3: 10_PD | C3: 地產處 | D3: Property Division | E3: Yes | F3: No
A4: 11_AIADIP | B4: 11_AIADIP | C4: 人工智能與數據策略 - 地產 | D4: AI and Data Intelligence - Properties | E4: Yes | F4: No
A5: 11_AIADIP | B5: 42_AIADIP | C5: 人工智能與數據策略 - 地產 | D5: AI and Data Intelligence - Properties | E5: Yes | F5: No
A6: 4_IP | B6: IP | C6: 海外地產 | D6: International Property | E6: Yes | F6: No
A7: 4_IP | B7: 4_IP | C7: 海外地產 | D7: International Property | E7: Yes | F7: No
A8: CAO | B8: CS | C8: 公司秘書部 | D8: Company Secretarial Department | E8: Yes | F8: No | G8: Company Secretarial Department
A9: CAO | B9: IT | C9: 資訊科技部 | D9: Information Technology Department | E9: Yes | F9: No | G9: Information Technology Department
A10: CAO | B10: LG | C10: 法律部 | D10: Legal Department | E10: Yes | F10: No | G10: Legal Department
A11: CAO | B11: LC | C11: 法務部 (中國, 海外與財務投資) | D11: Corporate Legal Counsel Dept (China, Overseas & Investments) | E11: Yes | F11: No | G11: Corporate Legal Counsel Dept (China, Overseas & Investments)
A12: CAO | B12: OA | C12: 行政部 | D12: Office Administration Department | E12: Yes | F12: No | G12: Office Administration Department
A13: CAO | B13: CAO | C13: 行政處 | D13: Administration Division | E13: Yes | F13: No | G13: Administration Division
A14: CD | B14: CV | C14: 中國地產處 | D14: China Property | E14: Yes | F14: No
A15: CD | B15: CV_SH | C15: China Property - Shanghai Office | D15: China Property - Shanghai Office | E15: Yes | F15: No
A16: CD | B16: 51_CD | C16: 中國地產 | D16: China Property | E16: Yes | F16: No
A17: CD | B17: 52_CD2 | C17: 中國地產 (投資) | D17: China Property (Investment) | E17: Yes | F17: No | G17: China Property (Investment)
A18: CE | B18: AD | C18: 集團內部審計部 | D18: Group Internal Audit Department | E18: Yes | F18: No | G18: Group Internal Audit Department
A19: CE | B19: CE | C19: 集團行政總裁辦公室 | D19: Group CEO's Office | E19: Yes | F19: No | G19: Group CEO's Office
A20: CE | B20: CT | C20: 顧問 | D20: Consultant | E20: Yes | F20: No | G20: Consultant
A21: CE | B21: HCO | C21: 榮譽主席辦公室 | D21: Honorary Chairman's Office | E21: Yes | F21: No | G21: Honorary Chairman's Office
A22: CE | B22: HR | C22: 人力資源部 | D22: Human Resources Department | E22: Yes | F22: No | G22: Human Resources Department
A23: CE | B23: VCO | C23: 副董事長及執行董事辦公室 | D23: Vice Chairman & Executive Director's Office | E23: Yes | F23: No | G23: Vice Chairman & Executive Director's Office
A24: CE | B24: GIA | D24: GROUP INTERNAL AUDIT | E24: No | F24: No
A25: CE | B25: LS | C25: 香港生命科技青年會 | D25: Hong Kong Life Sciences Society | E25: Yes | F25: No | G25: Hong Kong Life Sciences Society
A26: CE | B26: 1_CE | C26: 行政總裁辦公室 | D26: Group CEO's Office (Division) | E26: Yes | F26: No
A27: FD | B27: FA | C27: 財務及會計部 | D27: Finance & Accounts Department | E27: Yes | F27: No | G27: Finance & Accounts Department
A28: FD | B28: FI | D28: FINANCE & INVESTMENT | E28: No | F28: No
A29: FD | B29: GD | C29: 貨倉部 | D29: Godown Department | E29: Yes | F29: No | G29: Godown Department
A30: FD | B30: IV | D30: INVESTMENT | E30: No | F30: No
A31: FD | B31: MI | C31: 樓宇按揭及保險部 | D31: Housing Mortgage and Insurance Department | E31: No | F31: No
A32: FD | B32: RE | C32: 海外地產 | D32: INTERNATIONAL REAL ESTATE | E32: Yes | F32: No
A33: FD | B33: SH | D33: [Treasury] Shipping | E33: No | F33: No
A34: FD | B34: TS | C34: 資金部 | D34: Treasury Department | E34: Yes | F34: No | G34: Treasury Department
A35: FD | B35: 3_FD | C35: 財務處 | D35: Finance Division | E35: Yes | F35: No
A36: HP | B36: CN | C36: 建築部 | D36: Construction Department | E36: Yes | F36: No | G36: Construction Department
A37: HP | B37: DS | C37: 設計部 | D37: Design | E37: Yes | F37: No
A38: HP | B38: HKP | C38: 香港地產處 | D38: HONG KONG PROPERTY | E38: No | F38: No
A39: HP | B39: BV | C39: 業務價值推進部 | D39: BUSINESS VALUE ADVANCEMENT | E39: No | F39: No
A40: HP | B40: ML | C40: 南豐紗廠 | D40: The Mills | E40: Yes | F40: No | G40: The Mills
A41: HP | B41: PD | C41: 地產發展部 | D41: Property Development Department | E41: Yes | F41: No | G41: Property Development Department
A42: HP | B42: PJ | C42: 工程部 | D42: Project Department | E42: Yes | F42: No | G42: Project Department
A43: HP | B43: PMT | C43: 物業管理部 | D43: Property Management Department | E43: Yes | F43: No | G43: Property Management Department
A44: HP | B44: SL | C44: 資產管理部 | D44: Asset Management Department | E44: Yes | F44: No | G44: Asset Management Department
A45: HP | B45: SN | C45: 建築地盤 | D45: Site Construction | E45: Yes | F45: No | G45: Site Construction
A46: HP | B46: SP | C46: 銷售部 | D46: Sales Department | E46: Yes | F46: No | G46: Sales Department
A47: HP | B47: AX | D47: THE ANNEX | E47: No | F47: No
A48: HP | B48: MC | C48: Marketing and Communications | D48: Marketing and Communications | E48: Yes | F48: No
A49: HP | B49: GMDO | C49: 集團董事總經理辦公室 | D49: Hong Kong Property Group Managing Director's Office | E49: Yes | F49: No | G49: Hong Kong Property Group Managing Director's Office
A50: HP | B50: CCE | C50: CULTURAL & COMMUNITY ENGAGEMENT | D50: CULTURAL & COMMUNITY ENGAGEMENT | E50: No | F50: No
A51: HP | B51: BI | C51: SEWIT部 | D51: SEWIT Department | E51: Yes | F51: No | G51: SEWIT Department
A52: HP | B52: CRSA | C52: 客戶關係及諮詢部 | D52: Customer Relations & Service Assurance Department | E52: Yes | F52: No | G52: Customer Relations & Service Assurance Department
A53: HP | B53: 6_HP | C53: 香港地產 | D53: Hong Kong Property | E53: Yes | F53: No | G53: Hong Kong Property
A54: HP | B54: 64_MCR | C54: 市務及傳訊 (住宅) 部 | D54: Marketing and Communications (Residential) Department | E54: Yes | F54: No | G54: Marketing and Communications (Residential) Department
A55: HP | B55: 64_MCC | C55: 市務及傳訊 (商業) 部 | D55: Marketing and Communications (Commercial) Department | E55: Yes | F55: No | G55: Marketing and Communications (Commercial) Department
A56: LS | B56: PVTC | C56: Pivotal China | D56: Pivotal China | E56: Yes | F56: No
A57: LS | B57: 9_LS | C57: 生命科技 | D57: Life Sciences | E57: Yes | F57: No
A58: ML6 | B58: ML6 | C58: CHAT六廠 | D58: CHAT | E58: Yes | F58: No
A59: ML6 | B59: CUR | C59: 策展部 | D59: CURATORIAL | E59: No | F59: No
A60: ML6 | B60: COM | C60: 傳訊部 | D60: COMMUNICATIONS | E60: No | F60: No
A61: ML6 | B61: F&O | C61: 財務及營運部 | D61: FINANCE & OPERATIONS | E61: No | F61: No
A62: ML6 | B62: 7_ML6 | C62: CHAT六廠 | D62: CHAT (Mill6) | E62: Yes | F62: No
A63: NTR | B63: NTR | D63: Nan Fung Trinity | E63: Yes | F63: No | G63: Nan Fung Trinity
A64: NTR | B64: 8_NTR | C64: 財務投資處 | D64: Financial Investment Division | E64: Yes | F64: No
A65: OA Temp | B65: OA Temp | C65: OA Temp | D65: OA Temp | E65: Yes | F65: No

Sheet Sheet1
A1: MDM Department | B1: RMS Department
A2: [NFPGZ] Finance & Accounting Department | B2: {=INDEX(Table1[Department Name (Eng)],MATCH(Sheet1!A2,Table1[MDM Department],0),FALSE)} -> #N/A
A3: [NFPGZ] General Manager Office | B3: {=INDEX(Table1[Department Name (Eng)],MATCH(Sheet1!A3,Table1[MDM Department],0),FALSE)} -> #N/A
A4: [NFPGZ] Human Resources & Administration Department | B4: {=INDEX(Table1[Department Name (Eng)],MATCH(Sheet1!A4,Table1[MDM Department],0),FALSE)} -> #N/A
A5: [NFPGZ] Information Technology Department | B5: {=INDEX(Table1[Department Name (Eng)],MATCH(Sheet1!A5,Table1[MDM Department],0),FALSE)} -> #N/A
A6: [NFPGZ] Leasing Department-Mall | B6: {=INDEX(Table1[Department Name (Eng)],MATCH(Sheet1!A6,Table1[MDM Department],0),FALSE)} -> #N/A
A7: [NFPGZ] Operations Department | B7: {=INDEX(Table1[Department Name (Eng)],MATCH(Sheet1!A7,Table1[MDM Department],0),FALSE)} -> #N/A
A8: [NFPM] Asset Management | B8: {=INDEX(Table1[Department Name (Eng)],MATCH(Sheet1!A8,Table1[MDM Department],0),FALSE)} -> #N/A
A9: [NFPM] Development Management | B9: {=INDEX(Table1[Department Name (Eng)],MATCH(Sheet1!A9,Table1[MDM Department],0),FALSE)} -> #N/A
A10: [NFPM] Finance & Accounting | B10: {=INDEX(Table1[Department Name (Eng)],MATCH(Sheet1!A10,Table1[MDM Department],0),FALSE)} -> #N/A
A11: [NFPM] GM Office | B11: {=INDEX(Table1[Department Name (Eng)],MATCH(Sheet1!A11,Table1[MDM Department],0),FALSE)} -> #N/A
A12: [NFPM] Human Resources & Administration | B12: {=INDEX(Table1[Department Name (Eng)],MATCH(Sheet1!A12,Table1[MDM Department],0),FALSE)} -> #N/A
A13: [NFPM] IT | B13: {=INDEX(Table1[Department Name (Eng)],MATCH(Sheet1!A13,Table1[MDM Department],0),FALSE)} -> #N/A
... A61: Vice Chairman & Executive Director's Office | B61: {=INDEX(Table1[Department Name (Eng)],MATCH(Sheet1!A61,Table1[MDM Department],0),FALSE)} -> Vice Chairman & Executive Director's Office
